Reda_Utils/Utils.py
Reda_Utils/__init__.py
Reda_Utils/navegacion_move_base.py
Reda_Utils/navegacion_odometria_lib.py
Reda_Utils/tratamiento_logs.py
Reda_Utils-4.0.0.dist-info/METADATA
Reda_Utils-4.0.0.dist-info/WHEEL
Reda_Utils-4.0.0.dist-info/top_level.txt
Reda_Utils-4.0.0.dist-info/RECORD
