Metadata-Version: 2.1
Name: Reda-Utils
Version: 4.0.0
Summary: Paquete funciones utiles Navegacion Robot
Home-page: https://github.com/r3dkas/Reda_Utils
Author: Reda Kastite
Author-email: reda_kastite@hotmail.com
License: UNKNOWN
Platform: UNKNOWN
Classifier: Programming Language :: Python :: 2
Classifier: Programming Language :: Python :: 3
Classifier: License :: OSI Approved :: BSD License
Classifier: Operating System :: Unix
